slackerade/VERSION
slackerade/__init__.py
slackerade-0.0.2.dist-info/LICENSE
slackerade-0.0.2.dist-info/METADATA
slackerade-0.0.2.dist-info/WHEEL
slackerade-0.0.2.dist-info/entry_points.txt
slackerade-0.0.2.dist-info/top_level.txt
slackerade-0.0.2.dist-info/RECORD
