Metadata-Version: 2.1
Name: slackerade
Version: 0.0.2
Summary: Masquerade yourself as a fictitious user on slack
Home-page: https://github.com/KraYmer/slackerade
Author: Fabrice Laporte
Author-email: kraymer@gmail.com
License: MIT
Keywords: Masquerade yourself as a fictitious user on slack
Platform: ALL
Classifier: License :: OSI Approved :: MIT License
Classifier: Programming Language :: Python
Classifier: Topic :: Communications :: Chat
Requires-Python: >=3.5.0
Requires-Dist: requests
Requires-Dist: click
